proxy_webshare/__init__.py
proxy_webshare/database.py
proxy_webshare/response.py
proxy_webshare/webshare.py
proxy_webshare-1.0.0.dist-info/WHEEL
proxy_webshare-1.0.0.dist-info/METADATA
proxy_webshare-1.0.0.dist-info/RECORD
