Metadata-Version: 2.1
Name: proxy-webshare
Version: 1.0.0
Summary: 
Author: Antoni Oktha Fernandes
Author-email: 37358597+DesKaOne@users.noreply.github.com
Requires-Python: >=3.8,<4.0
Classifier: Programming Language :: Python :: 3
Classifier: Programming Language :: Python :: 3.8
Classifier: Programming Language :: Python :: 3.9
Classifier: Programming Language :: Python :: 3.10
Classifier: Programming Language :: Python :: 3.11
Requires-Dist: http-injector (>=1.0.3,<2.0.0)
Requires-Dist: sqlalchemy (>=2.0.29,<3.0.0)
Requires-Dist: sqlalchemy-utils (>=0.41.2,<0.42.0)
